mdigest/__init__.py
mdigest/core/__init__.py
mdigest/core/analysis.py
mdigest/core/auxiliary.py
mdigest/core/correlation.py
mdigest/core/dcorrelation.py
mdigest/core/dimreduction.py
mdigest/core/imports.py
mdigest/core/kscorrelation.py
mdigest/core/networkcanvas.py
mdigest/core/networkcommunities.py
mdigest/core/parsetrajectory.py
mdigest/core/savedata.py
mdigest/core/toolkit.py
mdigest/core/plots/__init__.py
mdigest/core/plots/dim_reduction_plots.py
mdigest/core/plots/general_plots.py
mdigest/core/plots/plot_correlation.py
mdigest/core/plots/__pycache__/__init__.cpython-310.pyc
mdigest/core/plots/__pycache__/__init__.cpython-38.pyc
mdigest/core/plots/__pycache__/dim_reduction_plots.cpython-310.pyc
mdigest/core/plots/__pycache__/dim_reduction_plots.cpython-38.pyc
mdigest/core/plots/__pycache__/general_plots.cpython-310.pyc
mdigest/core/plots/__pycache__/general_plots.cpython-38.pyc
mdigest/core/plots/__pycache__/plot_correlation.cpython-310.pyc
mdigest/core/plots/__pycache__/plot_correlation.cpython-38.pyc
mdigest/utils/__init__.py
mdigest/utils/imports.py
mdigest/utils/pdbhandler.py
mdigest/utils/simulation.py
mdigest/utils/toolkit.py
mdigest-0.1.9.dist-info/LICENSE
mdigest-0.1.9.dist-info/METADATA
mdigest-0.1.9.dist-info/WHEEL
mdigest-0.1.9.dist-info/top_level.txt
mdigest-0.1.9.dist-info/RECORD
